{
  "$schema": "https://json-schema.org/draft/2020-12/schema",
  "description": "Insight Series 製品定義",
  "version": "1.0.0",
  "products": {
    "desktop": [
      {
        "id": "sales-insight",
        "code": "SALES",
        "name": "SalesInsight",
        "displayName": "SalesInsight",
        "description": "AI営業支援アシスタント",
        "category": "sales",
        "platform": ["windows", "macos"],
        "framework": "tauri",
        "status": "active",
        "repository": "HarmonicInsight/SalesInsight",
        "features": [
          "realtime-analysis",
          "talk-optimization",
          "crm-integration"
        ]
      },
      {
        "id": "harmonic-sheet",
        "code": "HMSH",
        "name": "HarmonicSheet",
        "displayName": "HarmonicSheet",
        "description": "AI版管理付きスプレッドシート",
        "category": "office",
        "platform": ["windows"],
        "framework": "wpf",
        "status": "active",
        "repository": "HarmonicInsight/app-Insight-excel",
        "releasesRepository": "HarmonicInsight/releases",
        "sharedLibrary": "HarmonicInsight.Common",
        "features": [
          "excel-read-write",
          "version-control",
          "diff-compare",
          "ai-assistant",
          "team-board",
          "change-log"
        ]
      },
      {
        "id": "harmonic-doc",
        "code": "HMDC",
        "name": "HarmonicDoc",
        "displayName": "HarmonicDoc",
        "description": "AIドキュメント校正・バージョン管理",
        "category": "office",
        "platform": ["windows"],
        "framework": "wpf",
        "status": "active",
        "repository": "HarmonicInsight/app-Insight-doc",
        "releasesRepository": "HarmonicInsight/releases",
        "sharedLibrary": "HarmonicInsight.Common",
        "features": [
          "word-read-write",
          "version-control",
          "diff-compare",
          "ai-assistant",
          "reference-panel"
        ]
      },
      {
        "id": "insight-slide",
        "code": "INSS",
        "name": "InsightSlide",
        "displayName": "InsightSlide",
        "description": "AIスライドレビュー・バージョン管理",
        "category": "office",
        "platform": ["windows"],
        "framework": "wpf",
        "status": "active",
        "repository": "HarmonicInsight/app-Insight-slide",
        "releasesRepository": "HarmonicInsight/releases",
        "sharedLibrary": "HarmonicInsight.Common",
        "features": [
          "pptx-read-write",
          "version-control",
          "diff-compare",
          "ai-assistant",
          "batch-replace"
        ]
      },
      {
        "id": "insight-py",
        "code": "PY",
        "name": "InsightPy",
        "displayName": "InsightPy",
        "description": "Pythonデータ分析支援",
        "category": "data-analysis",
        "platform": ["windows", "macos", "linux"],
        "framework": "python",
        "status": "planned",
        "repository": "HarmonicInsight/InsightPy",
        "features": [
          "code-generation",
          "data-visualization",
          "report-creation"
        ]
      },
      {
        "id": "interview-insight",
        "code": "INTV",
        "name": "InterviewInsight",
        "displayName": "InterviewInsight",
        "description": "AI採用面接支援",
        "category": "hr",
        "platform": ["windows", "macos"],
        "framework": "tauri",
        "status": "planned",
        "repository": "HarmonicInsight/InterviewInsight",
        "features": [
          "interview-evaluation",
          "question-suggestion",
          "bias-detection"
        ]
      },
      {
        "id": "insight-forguncy",
        "code": "FORG",
        "name": "InsightForguncy",
        "displayName": "InsightForguncy",
        "description": "Forguncy AI開発支援",
        "category": "development",
        "platform": ["windows"],
        "framework": "tauri",
        "status": "development",
        "repository": "HarmonicInsight/app-win-insight-forguncy",
        "features": [
          "code-generation",
          "formula-assistance",
          "ui-optimization"
        ]
      },
      {
        "id": "insight-image-gen",
        "code": "INIG",
        "name": "InsightImageGen",
        "displayName": "InsightImageGen",
        "description": "AI画像・音声生成ツール（Stable Diffusion・VOICEVOX活用）",
        "category": "media",
        "platform": ["windows"],
        "framework": "wpf",
        "status": "active",
        "repository": "HarmonicInsight/app-insight-image-gen-C",
        "features": [
          "generate-image",
          "batch-image",
          "generate-audio",
          "character-prompts",
          "hi-res",
          "cloud-sync"
        ]
      },
      {
        "id": "insight-suite",
        "code": "ALL",
        "name": "Insight Suite",
        "displayName": "Insight Suite",
        "description": "全製品バンドル",
        "category": "bundle",
        "platform": ["windows", "macos"],
        "framework": "mixed",
        "status": "active",
        "repository": null,
        "features": ["all"]
      }
    ],
    "mobile": [
      {
        "id": "sales-insight-mobile",
        "code": "SALES-M",
        "name": "SalesInsight Mobile",
        "parentProduct": "sales-insight",
        "platform": ["ios", "android"],
        "framework": "react-native",
        "status": "planned"
      },
      {
        "id": "insight-slide-mobile",
        "code": "SLIDE-M",
        "name": "InsightSlide Mobile",
        "parentProduct": "insight-slide",
        "platform": ["ios", "android"],
        "framework": "react-native",
        "status": "planned"
      }
    ]
  },
  "tiers": {
    "TRIAL": {
      "name": "Trial",
      "duration": 14,
      "durationUnit": "days",
      "features": ["basic"],
      "limits": {
        "apiCalls": 100,
        "storage": "100MB"
      }
    },
    "STD": {
      "name": "Standard",
      "duration": 365,
      "durationUnit": "days",
      "features": ["basic", "standard"],
      "limits": {
        "apiCalls": 10000,
        "storage": "5GB"
      }
    },
    "PRO": {
      "name": "Professional",
      "duration": 365,
      "durationUnit": "days",
      "features": ["basic", "standard", "professional"],
      "limits": {
        "apiCalls": 100000,
        "storage": "50GB"
      }
    },
    "ENT": {
      "name": "Enterprise",
      "duration": null,
      "durationUnit": "perpetual",
      "features": ["basic", "standard", "professional", "enterprise"],
      "limits": {
        "apiCalls": "unlimited",
        "storage": "unlimited"
      }
    }
  },
  "featureFlags": {
    "basic": [
      "core-functionality",
      "local-processing"
    ],
    "standard": [
      "cloud-sync",
      "export-basic"
    ],
    "professional": [
      "team-collaboration",
      "advanced-analytics",
      "export-advanced",
      "api-access"
    ],
    "enterprise": [
      "sso",
      "audit-logs",
      "custom-deployment",
      "priority-support",
      "sla"
    ]
  }
}
